setup.py
bin/h4cli
h4_scripts/AuthorData.py
h4_scripts/Config.py
h4_scripts/Facebook.py
h4_scripts/Gmail.py
h4_scripts/GoogleSpreadsheetAPI.py
h4_scripts/Logger.py
h4_scripts/NetworkTest.py
h4_scripts/PTT.py
h4_scripts/Wikidot.py
h4_scripts/__init__.py
h4_scripts/common.py
h4_scripts.egg-info/PKG-INFO
h4_scripts.egg-info/SOURCES.txt
h4_scripts.egg-info/dependency_links.txt
h4_scripts.egg-info/top_level.txt
test/test_Facebook.py
test/test_FacebookGraph.py
test/test_Gmail.py
test/test_PTT.py
test/test_Wikidot.py