Metadata-Version: 1.0
Name: h4-scripts
Version: 0.9.1
Summary: Hacking Thursday automation scripts.
Home-page: https://github.com/hacking-thursday/h4-scripts
Author: Mat, yan
Author-email: matlinuxer2@gmail.com, a0726h77@gmail.com
License: MIT
Platform: UNKNOWN
